DNA_SE/DNA_SE.py
DNA_SE/__init__.py
DNA_SE/image.py
DNA_SE-0.1.2.dist-info/LICENSE.txt
DNA_SE-0.1.2.dist-info/METADATA
DNA_SE-0.1.2.dist-info/WHEEL
DNA_SE-0.1.2.dist-info/top_level.txt
DNA_SE-0.1.2.dist-info/RECORD
