Metadata-Version: 2.1
Name: DNA_SE
Version: 0.1.2
Summary: A small example package
Home-page: https://github.com/liuqs111/DNA-SE
Author: Qinshuo
Author-email: u3008680@connect.hku.hk
Classifier: Programming Language :: Python :: 3
Classifier: License :: OSI Approved :: MIT License
Classifier: Operating System :: OS Independent
Requires-Python: >=3.7
License-File: LICENSE.txt
